fclogr/__init__.py
fclogr/__main__.py
fclogr/_util.py
fclogr/py.typed
fclogr/cli/__init__.py
fclogr/cli/base.py
fclogr/cli/bump.py
fclogr/cli/dev_entries.py
fclogr/cli/sync.py
fclogr-0.13.0.dist-info/entry_points.txt
fclogr-0.13.0.dist-info/licenses/LICENSE
fclogr-0.13.0.dist-info/WHEEL
fclogr-0.13.0.dist-info/METADATA
fclogr-0.13.0.dist-info/RECORD
