Metadata-Version: 2.4
Name: fclogr
Version: 0.13.0
Summary: fclogr is a tool for managing RPM changelogs and updates
Author-email: Maxwell G <maxwell@gtmx.me>
Requires-Python: >=3.9
Classifier: Development Status :: 3 - Alpha
Classifier: Environment :: Console
Classifier: License :: OSI Approved :: GNU General Public License v2 or later (GPLv2+)
Classifier: Operating System :: POSIX :: Linux
Classifier: Programming Language :: Python
Classifier: Programming Language :: Python :: 3.9
Classifier: Programming Language :: Python :: 3.10
Classifier: Programming Language :: Python :: 3.11
Classifier: Programming Language :: Python :: 3.12
Classifier: Programming Language :: Python :: 3.13
Classifier: Typing :: Typed
License-File: LICENSE
Requires-Dist: pygit2
Requires-Dist: specfile
Requires-Dist: ruff ; extra == "codeqa"
Requires-Dist: reuse ; extra == "codeqa"
Requires-Dist: fclogr[codeqa] ; extra == "dev"
Requires-Dist: fclogr[formatters] ; extra == "dev"
Requires-Dist: fclogr[test] ; extra == "dev"
Requires-Dist: fclogr[typing] ; extra == "dev"
Requires-Dist: nox ; extra == "dev"
Requires-Dist: black >= 24 ; extra == "formatters"
Requires-Dist: isort ; extra == "formatters"
Requires-Dist: gitpython ; extra == "test"
Requires-Dist: pytest ; extra == "test"
Requires-Dist: pytest-mock ; extra == "test"
Requires-Dist: gitpython ; extra == "typing"
Requires-Dist: mypy ; extra == "typing"
Requires-Dist: pytest ; extra == "typing"
Requires-Dist: pytest-mock ; extra == "typing"
Requires-Dist: typing_extensions ; extra == "typing"
Requires-Dist: nox ; extra == "typing"
Project-URL: Changelog, https://git.sr.ht/~gotmax23/fclogr/tree/main/item/NEWS.md
Project-URL: Homepage, https://sr.ht/~gotmax23/fclogr
Project-URL: Mailing List, https://lists.sr.ht/~gotmax23/fclogr
Project-URL: Source, https://git.sr.ht/~gotmax23/fclogr
Provides-Extra: codeqa
Provides-Extra: dev
Provides-Extra: formatters
Provides-Extra: test
Provides-Extra: typing
